{"sections":{"cart-items":{"type":"main-cart-items","custom_css":["h1 {margin-bottom: 24px; font-family: \"Roboto\", sans-serif; font-weight: 600; color: black; text-align: center;}","div {background-color: white;}",".button {background: #1f5da0; color: white; padding: 15px 40px; font-weight: 600; transition: transform 0.3s ease, background-color 0.3s ease; overflow: hidden; text-decoration: none;}",".button:hover {background-color: #2a5cb8; transform: scale(1.05);}","h2, p {font-family: \"Roboto\", sans-serif; color: #222222; font-size: 16px;}","p>a {color: #1f5da0;}"],"settings":{"color_scheme":"","padding_top":36,"padding_bottom":36}},"cart-footer":{"type":"main-cart-footer","blocks":{"subtotal":{"type":"subtotal","settings":{}},"buttons":{"type":"buttons","settings":{}}},"block_order":["subtotal","buttons"],"settings":{"color_scheme":"","padding_top":40,"padding_bottom":40}}},"order":["cart-items","cart-footer"]}